[
  {
    "timestamp": "0-10",
    "title": "Shan Bombay Biryani Recipe | Chicken Biryani with Shan Masala | Shan Chicken Biryani Recipe",
    "url": "https://www.youtube.com/watch?v=dIieqJP1mac&t=0s",
    "ingredients": [
      "Chicken pieces",
      "Yellow rice",
      "White rice",
      "Vegetables (e.g., carrots)"
    ],
    "utensils": [
      "Plate"
    ],
    "actions": [
      "Serving biryani"
    ]
  },
  {
    "timestamp": "10-20",
    "title": "Shan Bombay Biryani Recipe | Chicken Biryani with Shan Masala | Shan Chicken Biryani Recipe",
    "url": "https://www.youtube.com/watch?v=dIieqJP1mac&t=10s",
    "ingredients": [
      "Chicken pieces",
      "White rice",
      "Grated coconut",
      "Curry/spice mix",
      "Green herbs (cilantro)",
      "Saffron strands",
      "Turmeric powder"
    ],
    "utensils": [
      "Metal bowl",
      "Spoon for garnishing"
    ],
    "actions": [
      "Placing chicken on rice",
      "Sprinkling grated coconut",
      "Adding green herbs",
      "Adding saffron strands and turmeric powder"
    ]
  },
  {
    "timestamp": "20-30",
    "title": "Shan Bombay Biryani Recipe | Chicken Biryani with Shan Masala | Shan Chicken Biryani Recipe",
    "url": "https://www.youtube.com/watch?v=dIieqJP1mac&t=20s",
    "ingredients": [
      "Yellow food coloring or turmeric (used to color the rice)",
      "Orange threads (likely saffron)",
      "Fresh green herbs (likely cilantro or curry leaves)",
      "Plain yogurt"
    ],
    "utensils": [
      "Metal serving spoon or spatula",
      "Glass bowl"
    ],
    "actions": [
      "Mixing rice with colored liquids and spices",
      "Placing yogurt into a glass bowl"
    ]
  },
  {
    "timestamp": "30-40",
    "title": "Shan Bombay Biryani Recipe | Chicken Biryani with Shan Masala | Shan Chicken Biryani Recipe",
    "url": "https://www.youtube.com/watch?v=dIieqJP1mac&t=30s",
    "ingredients": [
      "1 cup yogurt",
      "1 packet (Shan Bombay Biryani Masala)"
    ],
    "utensils": [
      "A glass bowl"
    ],
    "actions": [
      "Holding yogurt packet",
      "Pouring masala packet into bowl",
      "Adding masala to yogurt in bowl"
    ]
  },
  {
    "timestamp": "40-50",
    "title": "Shan Bombay Biryani Recipe | Chicken Biryani with Shan Masala | Shan Chicken Biryani Recipe",
    "url": "https://www.youtube.com/watch?v=dIieqJP1mac&t=40s",
    "ingredients": [
      "Turmeric powder",
      "Milk (or a milky liquid)",
      "Saffron threads"
    ],
    "utensils": [
      "Metal spoon",
      "Measuring cup",
      "Glass bowl"
    ],
    "actions": [
      "Pouring turmeric powder into a glass bowl",
      "Holding saffron threads in a glass bowl",
      "Stirring the mixture in the bowl"
    ]
  },
  {
    "timestamp": "50-60",
    "title": "Shan Bombay Biryani Recipe | Chicken Biryani with Shan Masala | Shan Chicken Biryani Recipe",
    "url": "https://www.youtube.com/watch?v=dIieqJP1mac&t=50s",
    "ingredients": [
      "Orange-colored powder (likely turmeric)",
      "Plain yogurt"
    ],
    "utensils": [
      "Glass bowl",
      "Metal spoon"
    ],
    "actions": [
      "Mixing yogurt and turmeric powder"
    ]
  },
  {
    "timestamp": "60-70",
    "title": "Shan Bombay Biryani Recipe | Chicken Biryani with Shan Masala | Shan Chicken Biryani Recipe",
    "url": "https://www.youtube.com/watch?v=dIieqJP1mac&t=60s",
    "ingredients": [
      "Coriander powder"
    ],
    "utensils": [
      "Glass bowl",
      "Spoon"
    ],
    "actions": [
      "Mixing spices",
      "Adding coriander powder"
    ]
  },
  {
    "timestamp": "70-80",
    "title": "Shan Bombay Biryani Recipe | Chicken Biryani with Shan Masala | Shan Chicken Biryani Recipe",
    "url": "https://www.youtube.com/watch?v=dIieqJP1mac&t=70s",
    "ingredients": [
      "Green-crumbed powder (likely a spice)",
      "Red chili powder",
      "Turmeric powder",
      "Garam masala powder"
    ],
    "utensils": [
      "Glass bowl",
      "Metal spoon",
      "Small glass container for spices"
    ],
    "actions": [
      "Adding green-crumbed powder to the bowl",
      "Adding red chili powder to the bowl",
      "Adding turmeric powder to the bowl",
      "Adding garam masala powder to the bowl"
    ]
  },
  {
    "timestamp": "80-90",
    "title": "Shan Bombay Biryani Recipe | Chicken Biryani with Shan Masala | Shan Chicken Biryani Recipe",
    "url": "https://www.youtube.com/watch?v=dIieqJP1mac&t=80s",
    "ingredients": [
      "Various powders (likely spices such as turmeric, chili powder, and others)"
    ],
    "utensils": [
      "A glass bowl",
      "A spoon"
    ],
    "actions": [
      "Adding spices to the bowl",
      "Mixing the spices with a spoon"
    ]
  },
  {
    "timestamp": "90-100",
    "title": "Shan Bombay Biryani Recipe | Chicken Biryani with Shan Masala | Shan Chicken Biryani Recipe",
    "url": "https://www.youtube.com/watch?v=dIieqJP1mac&t=90s",
    "ingredients": [
      "Turmeric mixture (orange-colored paste)"
    ],
    "utensils": [
      "Glass bowl",
      "Spoon"
    ],
    "actions": [
      "Mixing turmeric mixture"
    ]
  },
  {
    "timestamp": "100-110",
    "title": "Shan Bombay Biryani Recipe | Chicken Biryani with Shan Masala | Shan Chicken Biryani Recipe",
    "url": "https://www.youtube.com/watch?v=dIieqJP1mac&t=100s",
    "ingredients": [
      "Turmeric powder",
      "Oil"
    ],
    "utensils": [
      "Measuring cup",
      "Spoon",
      "Mixing bowl",
      "Large cooking pot"
    ],
    "actions": [
      "Scooping turmeric powder",
      "Showing the pot with oil measurement"
    ]
  },
  {
    "timestamp": "110-120",
    "title": "Shan Bombay Biryani Recipe | Chicken Biryani with Shan Masala | Shan Chicken Biryani Recipe",
    "url": "https://www.youtube.com/watch?v=dIieqJP1mac&t=110s",
    "ingredients": [
      "Garlic cloves",
      "Oil"
    ],
    "utensils": [
      "Metal bowl"
    ],
    "actions": [
      "Adding oil to the bowl",
      "Placing garlic cloves into the bowl"
    ]
  },
  {
    "timestamp": "120-130",
    "title": "Shan Bombay Biryani Recipe | Chicken Biryani with Shan Masala | Shan Chicken Biryani Recipe",
    "url": "https://www.youtube.com/watch?v=dIieqJP1mac&t=120s",
    "ingredients": [
      "Medium-sized potatoes"
    ],
    "utensils": [
      "Metal bowl"
    ],
    "actions": [
      "Placing potatoes in a bowl"
    ]
  },
  {
    "timestamp": "130-140",
    "title": "Shan Bombay Biryani Recipe | Chicken Biryani with Shan Masala | Shan Chicken Biryani Recipe",
    "url": "https://www.youtube.com/watch?v=dIieqJP1mac&t=130s",
    "ingredients": [
      "Potatoes",
      "Oil"
    ],
    "utensils": [
      "Pot",
      "Wooden spatula"
    ],
    "actions": [
      "Frying potatoes",
      "Stirring potatoes in oil"
    ]
  },
  {
    "timestamp": "140-150",
    "title": "Shan Bombay Biryani Recipe | Chicken Biryani with Shan Masala | Shan Chicken Biryani Recipe",
    "url": "https://www.youtube.com/watch?v=dIieqJP1mac&t=140s",
    "ingredients": [
      "Potatoes"
    ],
    "utensils": [
      "Stainless steel pot",
      "Ladle"
    ],
    "actions": [
      "Adding potatoes to boiling liquid",
      "Stirring potatoes with a ladle"
    ]
  },
  {
    "timestamp": "150-160",
    "title": "Shan Bombay Biryani Recipe | Chicken Biryani with Shan Masala | Shan Chicken Biryani Recipe",
    "url": "https://www.youtube.com/watch?v=dIieqJP1mac&t=150s",
    "ingredients": [
      "Star anise",
      "Black cardamom",
      "Cinnamon stick",
      "Cloves",
      "Black pepper",
      "Green cardamom",
      "White cumin seed",
      "Bay leaf"
    ],
    "utensils": [
      "Metal pot or pressure cooker",
      "Saucer with printed design"
    ],
    "actions": [
      "Adding spices to the pot",
      "Stirring the contents of the pot"
    ]
  },
  {
    "timestamp": "160-170",
    "title": "Shan Bombay Biryani Recipe | Chicken Biryani with Shan Masala | Shan Chicken Biryani Recipe",
    "url": "https://www.youtube.com/watch?v=dIieqJP1mac&t=160s",
    "ingredients": [
      "Star anis",
      "Black cardamom",
      "Cinnamon stick",
      "Cloves",
      "Black pepper",
      "Green cardamom",
      "White cumin seeds",
      "Bay leaf",
      "Rice (not an ingredient, but present on the plate)"
    ],
    "utensils": [
      "Plate with a coffee design",
      "Wooden spoon"
    ],
    "actions": [
      "Placing spices on a plate",
      "Picking up spices with a wooden spoon"
    ]
  },
  {
    "timestamp": "170-180",
    "title": "Shan Bombay Biryani Recipe | Chicken Biryani with Shan Masala | Shan Chicken Biryani Recipe",
    "url": "https://www.youtube.com/watch?v=dIieqJP1mac&t=170s",
    "ingredients": [
      "Star anise",
      "Black cardamom",
      "Cinnamon stick",
      "Cloves",
      "Black pepper",
      "Green cardamom",
      "White cumin seed",
      "Bay leaf"
    ],
    "utensils": [
      "Plate",
      "Spatula",
      "Metal pot",
      "Spices (plate of spices shown as whole)"
    ],
    "actions": [
      "Adding spices to a pot",
      "Frying spices in oil",
      "Stirring spices with a spatula"
    ]
  },
  {
    "timestamp": "180-190",
    "title": "Shan Bombay Biryani Recipe | Chicken Biryani with Shan Masala | Shan Chicken Biryani Recipe",
    "url": "https://www.youtube.com/watch?v=dIieqJP1mac&t=180s",
    "ingredients": [
      "Oil",
      "Egg",
      "Cloves",
      "Cinnamon stick"
    ],
    "utensils": [
      "Cooking pot",
      "Spatula"
    ],
    "actions": [
      "Stirring eggs",
      "Adding raw chicken",
      "Frying spices"
    ]
  },
  {
    "timestamp": "190-200",
    "title": "Shan Bombay Biryani Recipe | Chicken Biryani with Shan Masala | Shan Chicken Biryani Recipe",
    "url": "https://www.youtube.com/watch?v=dIieqJP1mac&t=190s",
    "ingredients": [
      "Chicken pieces",
      "Oil",
      "Star anise",
      "Cloves"
    ],
    "utensils": [
      "Glass bowl",
      "Metal pot"
    ],
    "actions": [
      "Adding chicken to oil in the pot",
      "Pouring chicken into hot oil"
    ]
  },
  {
    "timestamp": "200-210",
    "title": "Shan Bombay Biryani Recipe | Chicken Biryani with Shan Masala | Shan Chicken Biryani Recipe",
    "url": "https://www.youtube.com/watch?v=dIieqJP1mac&t=200s",
    "ingredients": [
      "Chicken pieces (thighs and wings)"
    ],
    "utensils": [
      "A metal pan"
    ],
    "actions": [
      "Adding chicken pieces to hot oil",
      "Frying chicken pieces"
    ]
  },
  {
    "timestamp": "210-220",
    "title": "Shan Bombay Biryani Recipe | Chicken Biryani with Shan Masala | Shan Chicken Biryani Recipe",
    "url": "https://www.youtube.com/watch?v=dIieqJP1mac&t=210s",
    "ingredients": [
      "Raw chicken pieces (including thighs and wings)"
    ],
    "utensils": [
      "A stainless steel cooking pot",
      "A white ladle",
      "A metal stand or sieve (used to hold ingredients over the pot)"
    ],
    "actions": [
      "Adding chicken to oil",
      "Stirring chicken in oil",
      "Simmering chicken in pot"
    ]
  },
  {
    "timestamp": "220-230",
    "title": "Shan Bombay Biryani Recipe | Chicken Biryani with Shan Masala | Shan Chicken Biryani Recipe",
    "url": "https://www.youtube.com/watch?v=dIieqJP1mac&t=220s",
    "ingredients": [
      "Raw chicken pieces"
    ],
    "utensils": [
      "Stainless steel pot",
      "White spatula"
    ],
    "actions": [
      "Stirring chicken",
      "Moving chicken pieces in the pot"
    ]
  },
  {
    "timestamp": "230-240",
    "title": "Shan Bombay Biryani Recipe | Chicken Biryani with Shan Masala | Shan Chicken Biryani Recipe",
    "url": "https://www.youtube.com/watch?v=dIieqJP1mac&t=230s",
    "ingredients": [
      "Chicken pieces"
    ],
    "utensils": [
      "Stainless steel pan",
      "Wooden spoon"
    ],
    "actions": [
      "Stirring chicken pieces"
    ]
  },
  {
    "timestamp": "240-250",
    "title": "Shan Bombay Biryani Recipe | Chicken Biryani with Shan Masala | Shan Chicken Biryani Recipe",
    "url": "https://www.youtube.com/watch?v=dIieqJP1mac&t=240s",
    "ingredients": [
      "Chicken (raw pieces)",
      "Star anise",
      "Whole spices (possibly mustard seeds or black peppercorns)"
    ],
    "utensils": [
      "Large cooking pot",
      "Wooden spatula"
    ],
    "actions": [
      "Stirring chicken",
      "Adding spices to chicken"
    ]
  },
  {
    "timestamp": "250-260",
    "title": "Shan Bombay Biryani Recipe | Chicken Biryani with Shan Masala | Shan Chicken Biryani Recipe",
    "url": "https://www.youtube.com/watch?v=dIieqJP1mac&t=250s",
    "ingredients": [
      "Chicken pieces",
      "Ginger garlic paste"
    ],
    "utensils": [
      "Metal bowl or pot",
      "Small white bowl with floral design",
      "Purple spatula"
    ],
    "actions": [
      "Adding ginger garlic paste to chicken",
      "Mixing ingredients in the pot"
    ]
  },
  {
    "timestamp": "260-270",
    "title": "Shan Bombay Biryani Recipe | Chicken Biryani with Shan Masala | Shan Chicken Biryani Recipe",
    "url": "https://www.youtube.com/watch?v=dIieqJP1mac&t=260s",
    "ingredients": [
      "Chicken pieces",
      "Salt"
    ],
    "utensils": [
      "Measuring spoons (one white and one pink)",
      "Metal bowl"
    ],
    "actions": [
      "Adding salt to chicken",
      "Pouring seasoning over chicken"
    ]
  },
  {
    "timestamp": "270-280",
    "title": "Shan Bombay Biryani Recipe | Chicken Biryani with Shan Masala | Shan Chicken Biryani Recipe",
    "url": "https://www.youtube.com/watch?v=dIieqJP1mac&t=270s",
    "ingredients": [
      "Chicken pieces",
      "Ghee (clarified butter)",
      "Cumin seeds",
      "Garlic paste",
      "Turmeric powder",
      "Salt"
    ],
    "utensils": [
      "Wooden spoon"
    ],
    "actions": [
      "Adding turmeric powder",
      "Stirring chicken and spices",
      "Adding salt to the mixture"
    ]
  },
  {
    "timestamp": "280-290",
    "title": "Shan Bombay Biryani Recipe | Chicken Biryani with Shan Masala | Shan Chicken Biryani Recipe",
    "url": "https://www.youtube.com/watch?v=dIieqJP1mac&t=280s",
    "ingredients": [
      "Chicken",
      "Tomatoes"
    ],
    "utensils": [
      "Pot",
      "Spoon (pink in color)"
    ],
    "actions": [
      "Stirring chicken",
      "Adding tomatoes to the pot"
    ]
  },
  {
    "timestamp": "290-300",
    "title": "Shan Bombay Biryani Recipe | Chicken Biryani with Shan Masala | Shan Chicken Biryani Recipe",
    "url": "https://www.youtube.com/watch?v=dIieqJP1mac&t=290s",
    "ingredients": [
      "Diced tomatoes",
      "Frying oil (in the pan)",
      "Chicken pieces"
    ],
    "utensils": [
      "Metal cooking pot",
      "Plastic spoon"
    ],
    "actions": [
      "Adding tomatoes to the pot",
      "Stirring the mixture with a spoon"
    ]
  },
  {
    "timestamp": "300-310",
    "title": "Shan Bombay Biryani Recipe | Chicken Biryani with Shan Masala | Shan Chicken Biryani Recipe",
    "url": "https://www.youtube.com/watch?v=dIieqJP1mac&t=300s",
    "ingredients": [
      "Chicken pieces",
      "Red bell pepper strips",
      "Oil",
      "Garlic (possible, inferred from the presence in the cooking process)"
    ],
    "utensils": [
      "Stainless steel pot",
      "White silicone spatula"
    ],
    "actions": [
      "Stirring chicken and peppers",
      "Adding red bell pepper strips to the pot"
    ]
  },
  {
    "timestamp": "310-320",
    "title": "Shan Bombay Biryani Recipe | Chicken Biryani with Shan Masala | Shan Chicken Biryani Recipe",
    "url": "https://www.youtube.com/watch?v=dIieqJP1mac&t=310s",
    "ingredients": [
      "Chicken pieces",
      "Red bell peppers",
      "Orange-colored paste (likely a spice or curry paste)"
    ],
    "utensils": [
      "Metal mixing bowl",
      "Rubber spatula",
      "Glass container (presumably for holding the paste)"
    ],
    "actions": [
      "Adding spice paste to the mixture",
      "Stirring the mixture with a spatula"
    ]
  },
  {
    "timestamp": "320-330",
    "title": "Shan Bombay Biryani Recipe | Chicken Biryani with Shan Masala | Shan Chicken Biryani Recipe",
    "url": "https://www.youtube.com/watch?v=dIieqJP1mac&t=320s",
    "ingredients": [
      "Tomatoes",
      "Red bell peppers",
      "Chicken (pieces)",
      "Turmeric powder"
    ],
    "utensils": [
      "Mixing bowl"
    ],
    "actions": [
      "Pouring turmeric powder"
    ]
  },
  {
    "timestamp": "330-340",
    "title": "Shan Bombay Biryani Recipe | Chicken Biryani with Shan Masala | Shan Chicken Biryani Recipe",
    "url": "https://www.youtube.com/watch?v=dIieqJP1mac&t=330s",
    "ingredients": [
      "Pieces of chicken",
      "Red bell peppers",
      "Yellow bell peppers",
      "Turmeric powder",
      "Oil"
    ],
    "utensils": [
      "Cooking pot",
      "Spatula"
    ],
    "actions": [
      "Adding turmeric powder to the pot",
      "Mixing ingredients with the spatula"
    ]
  },
  {
    "timestamp": "340-350",
    "title": "Shan Bombay Biryani Recipe | Chicken Biryani with Shan Masala | Shan Chicken Biryani Recipe",
    "url": "https://www.youtube.com/watch?v=dIieqJP1mac&t=340s",
    "ingredients": [
      "Potatoes",
      "Chicken",
      "Tomatoes",
      "Curry powder or similar yellow spice",
      "Oil"
    ],
    "utensils": [
      "Ladle",
      "Metal pot or pan"
    ],
    "actions": [
      "Stirring ingredients",
      "Adding potatoes",
      "Mixing curry"
    ]
  },
  {
    "timestamp": "350-360",
    "title": "Shan Bombay Biryani Recipe | Chicken Biryani with Shan Masala | Shan Chicken Biryani Recipe",
    "url": "https://www.youtube.com/watch?v=dIieqJP1mac&t=350s",
    "ingredients": [
      "Chicken pieces",
      "Potatoes",
      "Tomatoes",
      "Onion gravy or paste",
      "Spices (visibly coated on ingredients)"
    ],
    "utensils": [
      "Large metal pot or cooking vessel",
      "Spoon for stirring",
      "Lid for covering the pot"
    ],
    "actions": [
      "Stirring the curry",
      "Placing a lid on the pot",
      "Covering the pot to cook or simmer"
    ]
  },
  {
    "timestamp": "360-370",
    "title": "Shan Bombay Biryani Recipe | Chicken Biryani with Shan Masala | Shan Chicken Biryani Recipe",
    "url": "https://www.youtube.com/watch?v=dIieqJP1mac&t=360s",
    "ingredients": [
      "Fried onions"
    ],
    "utensils": [
      "Ladle",
      "Metal pot"
    ],
    "actions": [
      "Adding fried onions to the pot",
      "Stirring the contents of the pot"
    ]
  },
  {
    "timestamp": "370-380",
    "title": "Shan Bombay Biryani Recipe | Chicken Biryani with Shan Masala | Shan Chicken Biryani Recipe",
    "url": "https://www.youtube.com/watch?v=dIieqJP1mac&t=370s",
    "ingredients": [
      "Fried onions",
      "Meat (possibly chicken) with red sauce",
      "Carrots",
      "Tomatoes"
    ],
    "utensils": [
      "Stainless steel bowl",
      "Pan or pot for cooking"
    ],
    "actions": [
      "Adding fried onions",
      "Cooking meat in a red sauce"
    ]
  },
  {
    "timestamp": "380-390",
    "title": "Shan Bombay Biryani Recipe | Chicken Biryani with Shan Masala | Shan Chicken Biryani Recipe",
    "url": "https://www.youtube.com/watch?v=dIieqJP1mac&t=380s",
    "ingredients": [
      "Pieces of chicken",
      "Red sauce or curry base",
      "Carrots",
      "Fried onions"
    ],
    "utensils": [
      "Metal bowl",
      "Pan or pot"
    ],
    "actions": [
      "Adding fried onions to the curry",
      "Stirring the curry"
    ]
  },
  {
    "timestamp": "390-400",
    "title": "Shan Bombay Biryani Recipe | Chicken Biryani with Shan Masala | Shan Chicken Biryani Recipe",
    "url": "https://www.youtube.com/watch?v=dIieqJP1mac&t=390s",
    "ingredients": [
      "Fried onions"
    ],
    "utensils": [
      "Metal bowl for serving fried onions",
      "Large pot for the curry"
    ],
    "actions": [
      "Adding fried onions to curry",
      "Mixing ingredients in the pot"
    ]
  },
  {
    "timestamp": "400-410",
    "title": "Shan Bombay Biryani Recipe | Chicken Biryani with Shan Masala | Shan Chicken Biryani Recipe",
    "url": "https://www.youtube.com/watch?v=dIieqJP1mac&t=400s",
    "ingredients": [
      "Red sauce (tomato-based)",
      "Yellow-colored chunks (potatoes or other vegetables)",
      "Fried onions"
    ],
    "utensils": [
      "Metal bowl (for holding fried onions)",
      "Cooking pot"
    ],
    "actions": [
      "Adding fried onions to the pot",
      "Mixing ingredients in the pot"
    ]
  },
  {
    "timestamp": "410-420",
    "title": "Shan Bombay Biryani Recipe | Chicken Biryani with Shan Masala | Shan Chicken Biryani Recipe",
    "url": "https://www.youtube.com/watch?v=dIieqJP1mac&t=410s",
    "ingredients": [
      "Shredded meat",
      "Tomato-based curry or sauce",
      "Vegetables (potentially potatoes or carrots)",
      "Oil or ghee (visible as bubbles on the surface)"
    ],
    "utensils": [
      "Glass container/bowl (for holding shredded meat)",
      "Cooking pot (for preparing the curry)"
    ],
    "actions": [
      "Adding shredded meat to the curry",
      "Stirring the curry (implied action, though not directly visible in the frames)"
    ]
  },
  {
    "timestamp": "420-430",
    "title": "Shan Bombay Biryani Recipe | Chicken Biryani with Shan Masala | Shan Chicken Biryani Recipe",
    "url": "https://www.youtube.com/watch?v=dIieqJP1mac&t=420s",
    "ingredients": [
      "Fried onions",
      "Tomatoes",
      "Spices (red-colored liquid indicates spices or sauce)",
      "Potatoes"
    ],
    "utensils": [
      "Cooking pan"
    ],
    "actions": [
      "Adding fried onions to the curry",
      "Stirring the curry"
    ]
  },
  {
    "timestamp": "430-440",
    "title": "Shan Bombay Biryani Recipe | Chicken Biryani with Shan Masala | Shan Chicken Biryani Recipe",
    "url": "https://www.youtube.com/watch?v=dIieqJP1mac&t=430s",
    "ingredients": [
      "Potatoes",
      "Red curry sauce",
      "Cooked shredded meat"
    ],
    "utensils": [
      "Spoon"
    ],
    "actions": [
      "Stirring curry"
    ]
  },
  {
    "timestamp": "440-450",
    "title": "Shan Bombay Biryani Recipe | Chicken Biryani with Shan Masala | Shan Chicken Biryani Recipe",
    "url": "https://www.youtube.com/watch?v=dIieqJP1mac&t=440s",
    "ingredients": [
      "Chopped green herbs (parsley)",
      "Meat",
      "Red sauce (tomato-based)",
      "Spices"
    ],
    "utensils": [
      "Wooden spoon/spatula",
      "Saucepan"
    ],
    "actions": [
      "Adding chopped herbs to the curry",
      "Stirring the curry with a wooden spoon",
      "Mixing the herbs into the curry"
    ]
  },
  {
    "timestamp": "450-460",
    "title": "Shan Bombay Biryani Recipe | Chicken Biryani with Shan Masala | Shan Chicken Biryani Recipe",
    "url": "https://www.youtube.com/watch?v=dIieqJP1mac&t=450s",
    "ingredients": [
      "Chunks of yellow fruit (possibly mango)",
      "Red sauce (tomato-based)",
      "Fresh green herbs (likely cilantro)",
      "Oil or ghee"
    ],
    "utensils": [
      "Ladle"
    ],
    "actions": [
      "Stirring curry",
      "Adding herbs to curry"
    ]
  },
  {
    "timestamp": "460-470",
    "title": "Shan Bombay Biryani Recipe | Chicken Biryani with Shan Masala | Shan Chicken Biryani Recipe",
    "url": "https://www.youtube.com/watch?v=dIieqJP1mac&t=460s",
    "ingredients": [
      "Chicken pieces",
      "Red and yellow curry sauce",
      "Fresh herbs (likely coriander)"
    ],
    "utensils": [
      "Metal pot",
      "Metal lid",
      "Cloth or towel to hold the lid"
    ],
    "actions": [
      "Covering the pot with a lid",
      "Lifting the pot lid using a cloth or towel"
    ]
  },
  {
    "timestamp": "470-480",
    "title": "Shan Bombay Biryani Recipe | Chicken Biryani with Shan Masala | Shan Chicken Biryani Recipe",
    "url": "https://www.youtube.com/watch?v=dIieqJP1mac&t=470s",
    "ingredients": [
      "Potatoes",
      "Curry sauce",
      "Tomatoes",
      "Herbs (possibly coriander leaves)"
    ],
    "utensils": [
      "Metal cooking pot",
      "Metal spatula or spoon"
    ],
    "actions": [
      "Adding mixture to the curry",
      "Stirring curry",
      "Mixing ingredients"
    ]
  },
  {
    "timestamp": "480-490",
    "title": "Shan Bombay Biryani Recipe | Chicken Biryani with Shan Masala | Shan Chicken Biryani Recipe",
    "url": "https://www.youtube.com/watch?v=dIieqJP1mac&t=480s",
    "ingredients": [
      "Chicken pieces",
      "Tomato-based sauce",
      "Herbs (possibly cilantro)"
    ],
    "utensils": [
      "Cooking pot",
      "Spatula"
    ],
    "actions": [
      "Stirring curry",
      "Mixing ingredients in the pot"
    ]
  },
  {
    "timestamp": "490-500",
    "title": "Shan Bombay Biryani Recipe | Chicken Biryani with Shan Masala | Shan Chicken Biryani Recipe",
    "url": "https://www.youtube.com/watch?v=dIieqJP1mac&t=490s",
    "ingredients": [
      "Water"
    ],
    "utensils": [
      "Stainless steel pot"
    ],
    "actions": [
      "Adding water to the pot"
    ]
  },
  {
    "timestamp": "500-510",
    "title": "Shan Bombay Biryani Recipe | Chicken Biryani with Shan Masala | Shan Chicken Biryani Recipe",
    "url": "https://www.youtube.com/watch?v=dIieqJP1mac&t=500s",
    "ingredients": [
      "Glass water",
      "Cinnamon stick",
      "Cumin seeds"
    ],
    "utensils": [
      "Stainless steel pot"
    ],
    "actions": [
      "Pouring water into the pot",
      "Adding a cinnamon stick to the pot",
      "Adding cumin seeds to the pot"
    ]
  },
  {
    "timestamp": "510-520",
    "title": "Shan Bombay Biryani Recipe | Chicken Biryani with Shan Masala | Shan Chicken Biryani Recipe",
    "url": "https://www.youtube.com/watch?v=dIieqJP1mac&t=510s",
    "ingredients": [
      "Cumin seeds",
      "Curry leaves",
      "Coriander leaves",
      "Bay leaf"
    ],
    "utensils": [
      "Cooking pan"
    ],
    "actions": [
      "Adding cumin seeds to the pan",
      "Adding curry leaves to the pan",
      "Adding coriander leaves to the pan"
    ]
  },
  {
    "timestamp": "520-530",
    "title": "Shan Bombay Biryani Recipe | Chicken Biryani with Shan Masala | Shan Chicken Biryani Recipe",
    "url": "https://www.youtube.com/watch?v=dIieqJP1mac&t=520s",
    "ingredients": [
      "Green leaves and herbs",
      "Cumin seeds",
      "Lemon juice"
    ],
    "utensils": [
      "A metal pan or skillet",
      "A small glass container"
    ],
    "actions": [
      "Adding lemon juice to the pan with herbs and spices"
    ]
  },
  {
    "timestamp": "530-540",
    "title": "Shan Bombay Biryani Recipe | Chicken Biryani with Shan Masala | Shan Chicken Biryani Recipe",
    "url": "https://www.youtube.com/watch?v=dIieqJP1mac&t=530s",
    "ingredients": [
      "Leaves (likely curry leaves)",
      "Bay leaves",
      "Cinnamon stick",
      "4 tbsp salt"
    ],
    "utensils": [
      "Large metal pot"
    ],
    "actions": [
      "Adding salt to the pot",
      "Placing ingredients in the pot"
    ]
  },
  {
    "timestamp": "540-550",
    "title": "Shan Bombay Biryani Recipe | Chicken Biryani with Shan Masala | Shan Chicken Biryani Recipe",
    "url": "https://www.youtube.com/watch?v=dIieqJP1mac&t=540s",
    "ingredients": [
      "Water",
      "Green curry leaves",
      "Cinnamon stick",
      "Cardamom pods",
      "Salt"
    ],
    "utensils": [
      "Metal bowl"
    ],
    "actions": [
      "Soaking spices and leaves in water"
    ]
  },
  {
    "timestamp": "550-560",
    "title": "Shan Bombay Biryani Recipe | Chicken Biryani with Shan Masala | Shan Chicken Biryani Recipe",
    "url": "https://www.youtube.com/watch?v=dIieqJP1mac&t=550s",
    "ingredients": [
      "Basmati rice",
      "Water",
      "Spices (e.g., cardamom, bay leaves, various herbs)"
    ],
    "utensils": [
      "Strainer or sieve"
    ],
    "actions": [
      "Straining water and herbs",
      "Preparing to add basmati rice"
    ]
  },
  {
    "timestamp": "560-570",
    "title": "Shan Bombay Biryani Recipe | Chicken Biryani with Shan Masala | Shan Chicken Biryani Recipe",
    "url": "https://www.youtube.com/watch?v=dIieqJP1mac&t=560s",
    "ingredients": [
      "1 kg basmati rice",
      "Water",
      "Green leaves (likely bay leaves or similar spices)"
    ],
    "utensils": [
      "Colander",
      "Pot (for boiling water)"
    ],
    "actions": [
      "Pouring rice into boiling water",
      "Stirring water with green leaves in a pot"
    ]
  },
  {
    "timestamp": "570-580",
    "title": "Shan Bombay Biryani Recipe | Chicken Biryani with Shan Masala | Shan Chicken Biryani Recipe",
    "url": "https://www.youtube.com/watch?v=dIieqJP1mac&t=570s",
    "ingredients": [
      "Rice",
      "Water",
      "Green herbs (likely coriander leaves)"
    ],
    "utensils": [
      "Pink bowl",
      "Pot (for soaking rice)"
    ],
    "actions": [
      "Washing rice",
      "Pouring water over rice",
      "Stirring rice in bowl"
    ]
  },
  {
    "timestamp": "580-590",
    "title": "Shan Bombay Biryani Recipe | Chicken Biryani with Shan Masala | Shan Chicken Biryani Recipe",
    "url": "https://www.youtube.com/watch?v=dIieqJP1mac&t=580s",
    "ingredients": [
      "Basmati rice.",
      "Bay leaves.",
      "Whole spices.",
      "Green herbs (likely coriander leaves)."
    ],
    "utensils": [
      "Wooden spoon.",
      "A pot or cooking vessel."
    ],
    "actions": [
      "Pouring water.",
      "Adding rice to the pot.",
      "Stirring the rice and herbs."
    ]
  },
  {
    "timestamp": "590-600",
    "title": "Shan Bombay Biryani Recipe | Chicken Biryani with Shan Masala | Shan Chicken Biryani Recipe",
    "url": "https://www.youtube.com/watch?v=dIieqJP1mac&t=590s",
    "ingredients": [
      "Herbs (green leafy pieces, likely curry leaves)",
      "Red chili pepper"
    ],
    "utensils": [
      "Metal ladle"
    ],
    "actions": [
      "Stirring soup",
      "Adding herbs and chili to the soup"
    ]
  },
  {
    "timestamp": "600-610",
    "title": "Shan Bombay Biryani Recipe | Chicken Biryani with Shan Masala | Shan Chicken Biryani Recipe",
    "url": "https://www.youtube.com/watch?v=dIieqJP1mac&t=600s",
    "ingredients": [
      "Rice",
      "Water",
      "Bay leaves",
      "Mustard seeds"
    ],
    "utensils": [
      "Pressure cooker"
    ],
    "actions": [
      "Adding ingredients (bay leaves, mustard seeds) to the rice and water mixture",
      "Stirring the rice mixture",
      "Covering the pressure cooker"
    ]
  },
  {
    "timestamp": "610-620",
    "title": "Shan Bombay Biryani Recipe | Chicken Biryani with Shan Masala | Shan Chicken Biryani Recipe",
    "url": "https://www.youtube.com/watch?v=dIieqJP1mac&t=610s",
    "ingredients": [
      "White rice",
      "Whole spices (visible cardamom pods and cloves)"
    ],
    "utensils": [
      "Large metal bowl",
      "Mixing spoon"
    ],
    "actions": [
      "Adding oil to rice",
      "Fluffing the rice"
    ]
  },
  {
    "timestamp": "620-630",
    "title": "Shan Bombay Biryani Recipe | Chicken Biryani with Shan Masala | Shan Chicken Biryani Recipe",
    "url": "https://www.youtube.com/watch?v=dIieqJP1mac&t=620s",
    "ingredients": [
      "Oil"
    ],
    "utensils": [
      "Metal bowl",
      "Ladle"
    ],
    "actions": [
      "Pouring oil into the bowl"
    ]
  },
  {
    "timestamp": "630-640",
    "title": "Shan Bombay Biryani Recipe | Chicken Biryani with Shan Masala | Shan Chicken Biryani Recipe",
    "url": "https://www.youtube.com/watch?v=dIieqJP1mac&t=630s",
    "ingredients": [
      "Oil"
    ],
    "utensils": [
      "Stainless steel bowl",
      "Spoon",
      "Plate"
    ],
    "actions": [
      "Pouring oil into the bowl",
      "Tipping the bowl to spread the oil"
    ]
  },
  {
    "timestamp": "640-650",
    "title": "Shan Bombay Biryani Recipe | Chicken Biryani with Shan Masala | Shan Chicken Biryani Recipe",
    "url": "https://www.youtube.com/watch?v=dIieqJP1mac&t=640s",
    "ingredients": [
      "Onion rings",
      "Possibly batter (dipping the onion rings)"
    ],
    "utensils": [
      "Metal bowl",
      "Plate with snacks",
      "Wooden table surface"
    ],
    "actions": [
      "Dipping onion rings into batter",
      "Placing onion rings on a plate"
    ]
  },
  {
    "timestamp": "650-660",
    "title": "Shan Bombay Biryani Recipe | Chicken Biryani with Shan Masala | Shan Chicken Biryani Recipe",
    "url": "https://www.youtube.com/watch?v=dIieqJP1mac&t=650s",
    "ingredients": [
      "Grated coconut"
    ],
    "utensils": [
      "Metal mixing bowl",
      "Spoon"
    ],
    "actions": [
      "Adding grated coconut to the bowl",
      "Mixing grated coconut in the bowl"
    ]
  },
  {
    "timestamp": "660-670",
    "title": "Shan Bombay Biryani Recipe | Chicken Biryani with Shan Masala | Shan Chicken Biryani Recipe",
    "url": "https://www.youtube.com/watch?v=dIieqJP1mac&t=660s",
    "ingredients": [
      "Cooked white rice"
    ],
    "utensils": [
      "Stainless steel bowl",
      "Metal spatula/spoon"
    ],
    "actions": [
      "Flipping rice",
      "Mixing rice"
    ]
  },
  {
    "timestamp": "670-680",
    "title": "Shan Bombay Biryani Recipe | Chicken Biryani with Shan Masala | Shan Chicken Biryani Recipe",
    "url": "https://www.youtube.com/watch?v=dIieqJP1mac&t=670s",
    "ingredients": [
      "Cooked white rice",
      "A dish of curry (possibly containing paneer or tofu)"
    ],
    "utensils": [
      "Metal bowl for rice",
      "Wooden spoon",
      "Plate with curry"
    ],
    "actions": [
      "Spooning curry onto rice"
    ]
  },
  {
    "timestamp": "680-690",
    "title": "Shan Bombay Biryani Recipe | Chicken Biryani with Shan Masala | Shan Chicken Biryani Recipe",
    "url": "https://www.youtube.com/watch?v=dIieqJP1mac&t=680s",
    "ingredients": [
      "White rice",
      "Chicken pieces in orange sauce"
    ],
    "utensils": [
      "Large round metal bowl (for serving rice)",
      "Smaller bowl containing chicken and sauce",
      "Serving spoon"
    ],
    "actions": [
      "Scooping chicken and sauce with a spoon",
      "Placing chicken and sauce on the rice"
    ]
  },
  {
    "timestamp": "690-700",
    "title": "Shan Bombay Biryani Recipe | Chicken Biryani with Shan Masala | Shan Chicken Biryani Recipe",
    "url": "https://www.youtube.com/watch?v=dIieqJP1mac&t=690s",
    "ingredients": [
      "Chicken pieces",
      "Rice",
      "Red sauce",
      "Oranges (possibly boiled or marinated fruits)",
      "Fresh green herbs (e.g., cilantro)"
    ],
    "utensils": [
      "Metal bowl",
      "Another container holding red sauce"
    ],
    "actions": [
      "Pawning chicken pieces over rice",
      "Sprinkling fresh green herbs over the chicken and rice"
    ]
  },
  {
    "timestamp": "700-710",
    "title": "Shan Bombay Biryani Recipe | Chicken Biryani with Shan Masala | Shan Chicken Biryani Recipe",
    "url": "https://www.youtube.com/watch?v=dIieqJP1mac&t=700s",
    "ingredients": [
      "Marinated chicken pieces",
      "White rice",
      "Fresh green herbs (likely coriander)",
      "Orange sauce (potentially curry or gravy)"
    ],
    "utensils": [
      "Metal bowl",
      "Hand to garnish"
    ],
    "actions": [
      "Garnishing dish with herbs",
      "Serving chicken with rice"
    ]
  },
  {
    "timestamp": "710-720",
    "title": "Shan Bombay Biryani Recipe | Chicken Biryani with Shan Masala | Shan Chicken Biryani Recipe",
    "url": "https://www.youtube.com/watch?v=dIieqJP1mac&t=710s",
    "ingredients": [
      "Basmati rice",
      "Chicken pieces cooked in curry",
      "Fresh green herbs (likely cilantro)",
      "Boilie or hard-boiled egg (orange-colored)"
    ],
    "utensils": [
      "Stainless steel serving bowl",
      "Wooden table surface"
    ],
    "actions": [
      "Placing curry on the rice",
      "Garnishing with fresh herbs"
    ]
  },
  {
    "timestamp": "720-730",
    "title": "Shan Bombay Biryani Recipe | Chicken Biryani with Shan Masala | Shan Chicken Biryani Recipe",
    "url": "https://www.youtube.com/watch?v=dIieqJP1mac&t=720s",
    "ingredients": [
      "Cooked meat",
      "Rice",
      "Cilantro (fresh coriander leaves)",
      "Sauce",
      "Spices (visible on the meat)",
      "Boilie (hard-boiled egg)"
    ],
    "utensils": [
      "Metal bowl",
      "Serving scoop"
    ],
    "actions": [
      "Adding rice to the bowl",
      "Distributing rice over the meat and sauce"
    ]
  },
  {
    "timestamp": "730-740",
    "title": "Shan Bombay Biryani Recipe | Chicken Biryani with Shan Masala | Shan Chicken Biryani Recipe",
    "url": "https://www.youtube.com/watch?v=dIieqJP1mac&t=730s",
    "ingredients": [
      "White rice",
      "Biryani curry (contains chunks of food and a red sauce)"
    ],
    "utensils": [
      "Metal serving tray or pot",
      "White ladle",
      "Aluminum tray with biryani curry"
    ],
    "actions": [
      "Spooning biryani curry",
      "Piling biryani curry onto rice"
    ]
  },
  {
    "timestamp": "740-750",
    "title": "Shan Bombay Biryani Recipe | Chicken Biryani with Shan Masala | Shan Chicken Biryani Recipe",
    "url": "https://www.youtube.com/watch?v=dIieqJP1mac&t=740s",
    "ingredients": [
      "Chunks of marinated meat",
      "White rice",
      "Orange-colored curry sauce",
      "Fresh green herbs (cilantro)"
    ],
    "utensils": [
      "Metal mixing bowl",
      "Small dish for garnish"
    ],
    "actions": [
      "Adding fresh herbs to the rice and curry mixture"
    ]
  },
  {
    "timestamp": "750-760",
    "title": "Shan Bombay Biryani Recipe | Chicken Biryani with Shan Masala | Shan Chicken Biryani Recipe",
    "url": "https://www.youtube.com/watch?v=dIieqJP1mac&t=750s",
    "ingredients": [
      "Sliced tomatoes",
      "Chopped green chilies",
      "Chopped green herbs (cilantro)",
      "Rice"
    ],
    "utensils": [
      "Metal bowl",
      "Strainer"
    ],
    "actions": [
      "Adding herbs to rice",
      "Placing the strainer aside"
    ]
  },
  {
    "timestamp": "760-770",
    "title": "Shan Bombay Biryani Recipe | Chicken Biryani with Shan Masala | Shan Chicken Biryani Recipe",
    "url": "https://www.youtube.com/watch?v=dIieqJP1mac&t=760s",
    "ingredients": [
      "White rice",
      "Herbs (likely cilantro)",
      "Curry vegetables (mix of spices and vegetables)"
    ],
    "utensils": [
      "Stainless steel bowl",
      "Spoon/spatula for mixing",
      "Wood surface for placement"
    ],
    "actions": [
      "Adding rice to the bowl",
      "Mixing rice and vegetables using a spoon/spatula",
      "Leveling the surface of the rice"
    ]
  },
  {
    "timestamp": "770-780",
    "title": "Shan Bombay Biryani Recipe | Chicken Biryani with Shan Masala | Shan Chicken Biryani Recipe",
    "url": "https://www.youtube.com/watch?v=dIieqJP1mac&t=770s",
    "ingredients": [
      "Yellow food color",
      "Kewra water"
    ],
    "utensils": [
      "Large round metal bowl"
    ],
    "actions": [
      "Adding yellow food color to white rice",
      "Adding kewra water to white rice"
    ]
  },
  {
    "timestamp": "780-790",
    "title": "Shan Bombay Biryani Recipe | Chicken Biryani with Shan Masala | Shan Chicken Biryani Recipe",
    "url": "https://www.youtube.com/watch?v=dIieqJP1mac&t=780s",
    "ingredients": [
      "White rice",
      "Turmeric (yellow spice)",
      "Cinnamon stick"
    ],
    "utensils": [
      "Metal tray or bowl"
    ],
    "actions": [
      "Sprinkling turmeric",
      "Adding cinnamon sticks"
    ]
  },
  {
    "timestamp": "790-800",
    "title": "Shan Bombay Biryani Recipe | Chicken Biryani with Shan Masala | Shan Chicken Biryani Recipe",
    "url": "https://www.youtube.com/watch?v=dIieqJP1mac&t=790s",
    "ingredients": [
      "Cooked rice",
      "Yellow flower petals (likely from a flower like marigold)",
      "Thinly sliced or fried onions",
      "Fresh green herbs (likely coriander leaves)"
    ],
    "utensils": [
      "A large metal serving tray or bowl"
    ],
    "actions": [
      "Adding green herbs to rice",
      "Distributing yellow flower petals on the rice"
    ]
  },
  {
    "timestamp": "800-810",
    "title": "Shan Bombay Biryani Recipe | Chicken Biryani with Shan Masala | Shan Chicken Biryani Recipe",
    "url": "https://www.youtube.com/watch?v=dIieqJP1mac&t=800s",
    "ingredients": [
      "White rice",
      "Yellow flower petals",
      "Green herbs (likely curry leaves or cilantro)",
      "Red-orange saffron threads"
    ],
    "utensils": [
      "A metal serving tray or bowl"
    ],
    "actions": [
      "Placing a metal lid over the tray of rice",
      "Holding the lid on the tray"
    ]
  },
  {
    "timestamp": "810-820",
    "title": "Shan Bombay Biryani Recipe | Chicken Biryani with Shan Masala | Shan Chicken Biryani Recipe",
    "url": "https://www.youtube.com/watch?v=dIieqJP1mac&t=810s",
    "ingredients": [
      "Not applicable/inapplicable; no ingredients are visible in the frames provided."
    ],
    "utensils": [
      "Metal lid or plate"
    ],
    "actions": [
      "Not applicable/inapplicable; no actions are depicted in the frames provided."
    ]
  },
  {
    "timestamp": "820-830",
    "title": "Shan Bombay Biryani Recipe | Chicken Biryani with Shan Masala | Shan Chicken Biryani Recipe",
    "url": "https://www.youtube.com/watch?v=dIieqJP1mac&t=820s",
    "ingredients": [
      "Cooked white rice",
      "Yellow seasoning or food coloring",
      "Orange-colored seasoning or sauce",
      "Green herbs (possibly cilantro or curry leaves)"
    ],
    "utensils": [
      "Stainless steel pot or pan",
      "Metal spatula or fork"
    ],
    "actions": [
      "Adding seasonings to rice",
      "Mixing rice with a spatula or fork"
    ]
  },
  {
    "timestamp": "830-840",
    "title": "Shan Bombay Biryani Recipe | Chicken Biryani with Shan Masala | Shan Chicken Biryani Recipe",
    "url": "https://www.youtube.com/watch?v=dIieqJP1mac&t=830s",
    "ingredients": [
      "Cooked white rice",
      "Yellow-colored rice (likely saffron or turmeric)",
      "Brownish-red strands (possibly fried onions or caramelized onions)",
      "Green herbs (such as curry leaves or cilantro)"
    ],
    "utensils": [
      "Serving spoon or spatula"
    ],
    "actions": [
      "Mixing rice with yellow-colored rice and brownish-red strands"
    ]
  },
  {
    "timestamp": "840-850",
    "title": "Shan Bombay Biryani Recipe | Chicken Biryani with Shan Masala | Shan Chicken Biryani Recipe",
    "url": "https://www.youtube.com/watch?v=dIieqJP1mac&t=840s",
    "ingredients": [
      "Chicken pieces",
      "Steamed white rice",
      "Yellow rice (possibly saffron-infused)",
      "Vegetables (potatoes or similar items)"
    ],
    "utensils": [
      "Serving plate"
    ],
    "actions": [
      "Placing chicken pieces on cooked rice",
      "Arranging rice on the plate"
    ]
  },
  {
    "timestamp": "850-860",
    "title": "Shan Bombay Biryani Recipe | Chicken Biryani with Shan Masala | Shan Chicken Biryani Recipe",
    "url": "https://www.youtube.com/watch?v=dIieqJP1mac&t=850s",
    "ingredients": [
      "Chicken legs",
      "Yellow rice",
      "White rice",
      "Grated cheese",
      "Herbs (possibly cilantro)"
    ],
    "utensils": [
      "Plate"
    ],
    "actions": [
      "Serving food"
    ]
  },
  {
    "timestamp": "860-870",
    "title": "Shan Bombay Biryani Recipe | Chicken Biryani with Shan Masala | Shan Chicken Biryani Recipe",
    "url": "https://www.youtube.com/watch?v=dIieqJP1mac&t=860s",
    "ingredients": [
      "Chicken",
      "Basmati rice",
      "Grated cheese",
      "Herbs (possibly cilantro)",
      "Spices"
    ],
    "utensils": [
      "(No utensils are visible)"
    ],
    "actions": [
      "Presenting the cooked dish",
      "Placing the chicken on the rice",
      "Garnishing with cheese and herbs"
    ]
  },
  {
    "timestamp": "870-880",
    "title": "Shan Bombay Biryani Recipe | Chicken Biryani with Shan Masala | Shan Chicken Biryani Recipe",
    "url": "https://www.youtube.com/watch?v=dIieqJP1mac&t=870s",
    "ingredients": [
      "Chicken drumsticks",
      "Yellow rice",
      "White rice",
      "Grated cheese",
      "Herbs (possibly parsley or cilantro)"
    ],
    "utensils": [
      "Plate"
    ],
    "actions": [
      "Placing chicken on top of rice"
    ]
  },
  {
    "timestamp": "880-890",
    "title": "Shan Bombay Biryani Recipe | Chicken Biryani with Shan Masala | Shan Chicken Biryani Recipe",
    "url": "https://www.youtube.com/watch?v=dIieqJP1mac&t=880s",
    "ingredients": [
      "Chicken pieces",
      "Yellow and white rice"
    ],
    "utensils": [
      "Plate (not clearly visible, implied by the presentation of the dish)"
    ],
    "actions": [
      "No specific cooking actions are visible in the frames provided."
    ]
  },
  {
    "timestamp": "890-900",
    "title": "Shan Bombay Biryani Recipe | Chicken Biryani with Shan Masala | Shan Chicken Biryani Recipe",
    "url": "https://www.youtube.com/watch?v=dIieqJP1mac&t=890s",
    "ingredients": [
      "None visible"
    ],
    "utensils": [
      "None visible"
    ],
    "actions": [
      "None visible"
    ]
  },
  {
    "timestamp": "900-906",
    "title": "Shan Bombay Biryani Recipe | Chicken Biryani with Shan Masala | Shan Chicken Biryani Recipe",
    "url": "https://www.youtube.com/watch?v=dIieqJP1mac&t=900s",
    "ingredients": [
      "Not applicable (no ingredients visible)"
    ],
    "utensils": [
      "Not applicable (no utensils visible)"
    ],
    "actions": [
      "Not applicable (no cooking actions visible)"
    ]
  }
]